{
    "homepage": "https://a5m2.mmatsubara.com/",
    "checkver": {
        "url": "https://a5m2.mmatsubara.com/beta/",
        "re": "urchinTracker\\('/beta/a5m2_(.*)_x86.zip'\\);"
    },
    "version": "2.16.0_beta20",
    "bin": "A5M2.exe",
    "persist": "Portable",
    "shortcuts": [
        [
            "A5M2.exe",
            "A5M2"
        ]
    ],
    "architecture": {
        "64bit": {
            "url": "https://a5m2.mmatsubara.com/beta/a5m2_2.16.0_beta20_x64.zip",
            "hash": "3eb171fff4c852599acc26e5708ad3e5bd041aadb8bd66c63ef9ff0d66260917"
        },
        "32bit": {
            "url": "https://a5m2.mmatsubara.com/beta/a5m2_2.16.0_beta20_x86.zip",
            "hash": "138451c0e1784f02d64264d9c8b9b85407e0b2f05975d46978034c7fcae2b816"
        }
    },
    "autoupdate": {
        "architecture": {
            "64bit": {
                "url": "https://a5m2.mmatsubara.com/beta/a5m2_$version_x64.zip"
            },
            "32bit": {
                "url": "https://a5m2.mmatsubara.com/beta/a5m2_$version_x86.zip"
            }
        }
    }
}
